streamflow_lsf/__init__.py
streamflow_lsf/connector.py
streamflow_lsf/plugin.py
streamflow_lsf/version.py
streamflow_lsf/schemas/lsf.json
streamflow_lsf-0.0.1.dist-info/LICENSE
streamflow_lsf-0.0.1.dist-info/METADATA
streamflow_lsf-0.0.1.dist-info/WHEEL
streamflow_lsf-0.0.1.dist-info/entry_points.txt
streamflow_lsf-0.0.1.dist-info/top_level.txt
streamflow_lsf-0.0.1.dist-info/zip-safe
streamflow_lsf-0.0.1.dist-info/RECORD
