Metadata-Version: 2.1
Name: streamflow-lsf
Version: 0.0.1
Summary: StreamFlow LSF plugin
Author-email: Iacopo Colonnelli <iacopo.colonnelli@unito.it>, Alberto Mulone <alberto.mulone@unito.it>
License: LGPL-3.0-or-later
Project-URL: Repository, https://github.com/alpha-unito/streamflow-lsf
Classifier: Development Status :: 3 - Alpha
Classifier: License :: OSI Approved :: GNU Lesser General Public License v3 (LGPLv3)
Classifier: Intended Audience :: Science/Research
Classifier: Operating System :: POSIX
Classifier: Operating System :: MacOS
Classifier: Programming Language :: Python
Classifier: Programming Language :: Python :: 3 :: Only
Classifier: Programming Language :: Python :: 3.8
Classifier: Programming Language :: Python :: 3.9
Classifier: Programming Language :: Python :: 3.10
Classifier: Programming Language :: Python :: 3.11
Classifier: Programming Language :: Python :: 3.12
Classifier: Topic :: Scientific/Engineering
Classifier: Topic :: System :: Distributed Computing
Requires-Python: >=3.8
License-File: LICENSE
Requires-Dist: streamflow ==0.2.0.dev11
